<?xml version="1.0" encoding="UTF-8" ?>
<ns:Documents Version="1.0" xmlns:xsi="http://www.w3.org/2001/XMLSchema-instance" xmlns:ns="http://fsrar.ru/WEGAIS/WB_DOC_SINGLE_01" xmlns:pref="http://fsrar.ru/WEGAIS/ProductRef_v2" xmlns:awr="http://fsrar.ru/WEGAIS/ActWriteOff_v2" xmlns:ce="http://fsrar.ru/WEGAIS/CommonEnum">
	<ns:Owner>
		<ns:FSRAR_ID>{0}</ns:FSRAR_ID>
	</ns:Owner>
	<ns:Document>
		<ns:ActWriteOff_v2>
			<awr:Header>
				<awr:ActNumber>{1}</awr:ActNumber>
				<awr:ActDate>{2}</awr:ActDate>
				<awr:TypeWriteOff>{3}</awr:TypeWriteOff>
			</awr:Header>
			<awr:Content />
		</ns:ActWriteOff_v2>
	</ns:Document>
</ns:Documents>